{
  "judoka_1": {
    "bg_color": "ffd273",
    "desc_locked": "Judoka",
    "desc_unlocked": "The Judoka has the power to control computers with the mind, and guides new wizards through the worlds of Kano.",
    "operation": "each_greater",
    "targets": [["computed", "kano_level", 1]],
    "title": "Judoka 1"
  },
  "judoka_2": {
    "bg_color": "f2c25c",
    "desc_locked": "Judoka",
    "desc_unlocked": "Judoka can travel around the world through the Internet, and loves sea-urchin sushi and throwing code blocks at bad guys – the evil Robotniks, who eat up beautiful computers and turn them into boring grey boxes.",
    "operation": "each_greater",
    "targets": [["computed", "kano_level", 1]],
    "title": "Judoka 2"
  },
  "judoka_3": {
    "bg_color": "ffc852",
    "desc_locked": "Judoka",
    "desc_unlocked": "Judoka has the power to go from real, to digital all the way to terminal based – in the blink of an eye! Sometimes the effect runs off over time, so 0's and 1's can hang around like a digital aura.",
    "operation": "each_greater",
    "targets": [["computed", "kano_level", 1]],
    "title": "Judoka 3"
  }
}
