{
  "make-snake": {
    "level": {
      "1": 5,
      "2": 5,
      "3": 10,
      "4": 10,
      "5": 20,
      "6": 35,
      "7": 55,
      "8": 70,
      "9": 90
    },
    "multipliers": {
      "highest_score": 0.01,
      "longest_snake": 0.1,
      "total_length": 0.02,
      "total_number_of_apples": 0.01,
      "total_score": 0.0001
    }
  },
  "make-pong": {
    "level": {
      "1": 5,
      "2": 5,
      "3": 7,
      "4": 7,
      "5": 10,
      "6": 10,
      "7": 20,
      "8": 20,
      "9": 35,
      "10": 35,
      "11": 55,
      "12": 55,
      "13": 75,
      "14": 75,
      "15": 86
    },
    "multipliers": {
      "shared": 1
    }
  },
  "kano-draw": {
    "level": {
      "1": 5,
      "2": 5,
      "3": 7,
      "4": 7,
      "5": 10,
      "6": 10,
      "7": 20,
      "8": 20,
      "9": 35,
      "10": 35,
      "11": 55,
      "12": 55,
      "13": 75,
      "14": 75,
      "15": 86
    },
    "multipliers": {
      "shared": 1
    }
  },
  "linux-story": {
    "level": {
      "1": 5,
      "2": 10,
      "3": 15,
      "4": 25,
      "5": 35,
      "6": 50,
      "7": 70,
      "8": 90
    }
  },
  "make-minecraft": {
    "level": {
      "1": 5,
      "2": 7,
      "3": 10,
      "4": 10,
      "5": 20,
      "6": 20,
      "7": 35,
      "8": 35,
      "9": 55,
      "10": 55,
      "11": 75,
      "12": 80,
      "13": 93
    },
    "multipliers": {
      "shared": 1
    }
  },
  "kano-settings": {
    "multipliers": {
      "completed": 1
    }
  }
}
